bookdatamaker/__init__.py
bookdatamaker/cli.py
bookdatamaker/dataset/__init__.py
bookdatamaker/dataset/builder.py
bookdatamaker/dataset/dataset_manager.py
bookdatamaker/llm/__init__.py
bookdatamaker/llm/parallel_generator.py
bookdatamaker/mcp/__init__.py
bookdatamaker/mcp/server.py
bookdatamaker/ocr/__init__.py
bookdatamaker/ocr/document_parser.py
bookdatamaker/ocr/extractor.py
bookdatamaker/utils/__init__.py
bookdatamaker/utils/page_manager.py
bookdatamaker/utils/status.py
bookdatamaker-0.2.2.dist-info/licenses/LICENSE
bookdatamaker-0.2.2.dist-info/METADATA
bookdatamaker-0.2.2.dist-info/WHEEL
bookdatamaker-0.2.2.dist-info/entry_points.txt
bookdatamaker-0.2.2.dist-info/top_level.txt
bookdatamaker-0.2.2.dist-info/RECORD
