Metadata-Version: 2.4
Name: bookdatamaker
Version: 0.2.2
Summary: CLI tool for extracting text with DeepSeek OCR and generating datasets
Author-email: zwh20081 <zwh20081@solart.pro>
License: MIT
Requires-Python: <3.13,>=3.10
License-File: LICENSE
Requires-Dist: click
Requires-Dist: httpx
Requires-Dist: openai
Requires-Dist: mcp
Requires-Dist: pyarrow
Requires-Dist: pandas
Requires-Dist: python-dotenv
Requires-Dist: rich
Requires-Dist: aiofiles
Requires-Dist: Pillow
Requires-Dist: tqdm
Requires-Dist: PyMuPDF
Requires-Dist: ebooklib
Requires-Dist: beautifulsoup4
Provides-Extra: local
Requires-Dist: transformers==4.46.3; extra == "local"
Requires-Dist: torch; extra == "local"
Requires-Dist: flash-attn; extra == "local"
Requires-Dist: einops; extra == "local"
Requires-Dist: easydict; extra == "local"
Requires-Dist: addict; extra == "local"
Provides-Extra: document
Requires-Dist: PyMuPDF; extra == "document"
Requires-Dist: ebooklib; extra == "document"
Requires-Dist: beautifulsoup4; extra == "document"
Provides-Extra: all
Requires-Dist: transformers==4.46.3; extra == "all"
Requires-Dist: torch; extra == "all"
Requires-Dist: flash-attn; extra == "all"
Requires-Dist: einops; extra == "all"
Requires-Dist: easydict; extra == "all"
Requires-Dist: addict; extra == "all"
Requires-Dist: PyMuPDF; extra == "all"
Requires-Dist: ebooklib; extra == "all"
Requires-Dist: beautifulsoup4; extra == "all"
Provides-Extra: dev
Requires-Dist: pytest; extra == "dev"
Requires-Dist: pytest-asyncio; extra == "dev"
Requires-Dist: black; extra == "dev"
Requires-Dist: ruff; extra == "dev"
Requires-Dist: mypy; extra == "dev"
Dynamic: license-file
